CHANGES.txt
MANIFEST.in
README.txt
setup.cfg
setup.py
docs/INSTALL.txt
docs/LICENSE.GPL
docs/LICENSE.txt
p4a/__init__.py
p4a.common.egg-info/PKG-INFO
p4a.common.egg-info/SOURCES.txt
p4a.common.egg-info/dependency_links.txt
p4a.common.egg-info/entry_points.txt
p4a.common.egg-info/namespace_packages.txt
p4a.common.egg-info/not-zip-safe
p4a.common.egg-info/requires.txt
p4a.common.egg-info/top_level.txt
p4a/common/__init__.py
p4a/common/at.py
p4a/common/atwidget.pt
p4a/common/configure.zcml
p4a/common/dtutils.py
p4a/common/feature.py
p4a/common/formatting.py
p4a/common/interfaces.py
p4a/common/migutils.py
p4a/common/pkgutils.py
p4a/common/site.py
p4a/common/testing.py
p4a/common/tests.py
p4a/common/descriptors/__init__.py
p4a/common/descriptors/_anno.py
p4a/common/descriptors/_at.py