Metadata-Version: 1.1
Name: p4a.common
Version: 1.1
Summary: Reusable code-bits for Zope 3 and Plone
Home-page: http://pypi.python.org/pypi/p4a.common/
Author: Rocky Burt
Author-email: rocky@serverzen.com
License: GPL
Keywords: plone4artists
Platform: UNKNOWN
Classifier: Framework :: Zope2
Classifier: Framework :: Zope3
Classifier: Framework :: Plone
Classifier: Programming Language :: Python
Classifier: Programming Language :: Python :: 2.6
Classifier: Programming Language :: Python :: 2.7
Classifier: Topic :: Software Development :: Libraries :: Python Modules
